Compiled from "OreData.java"
public class com.tom.createores.OreData {
  private net.minecraft.resources.ResourceLocation recipe;

  private boolean loaded;

  private long extractedAmount;

  private float randomMul;

  private java.util.Set<net.minecraft.core.BlockPos> extractors;

  public static final com.mojang.serialization.Codec<com.tom.createores.OreData> CODEC;

  public com.tom.createores.OreData();
    Code:
         0: aload_0
         1: invokespecial #1                  // Method java/lang/Object."<init>":()V
         4: return

  public com.tom.createores.OreData(com.tom.createores.OreData$Serialized);
    Code:
         0: aload_0
         1: invokespecial #1                  // Method java/lang/Object."<init>":()V
         4: aload_0
         5: aload_1
         6: invokevirtual #7                  // Method load:(Lcom/tom/createores/OreData$Serialized;)V
         9: return

  public void load(com.tom.createores.OreData$Serialized);
    Code:
         0: aload_0
         1: aload_1
         2: invokevirtual #13                 // Method com/tom/createores/OreData$Serialized.loaded:()Z
         5: putfield      #19                 // Field loaded:Z
         8: aload_0
         9: aload_1
        10: invokevirtual #22                 // Method com/tom/createores/OreData$Serialized.recipe:()Ljava/util/Optional;
        13: aconst_null
        14: invokevirtual #26                 // Method java/util/Optional.orElse:(Ljava/lang/Object;)Ljava/lang/Object;
        17: checkcast     #32                 // class net/minecraft/resources/ResourceLocation
        20: putfield      #34                 // Field recipe:Lnet/minecraft/resources/ResourceLocation;
        23: aload_0
        24: aload_1
        25: invokevirtual #37                 // Method com/tom/createores/OreData$Serialized.extracted:()J
        28: putfield      #41                 // Field extractedAmount:J
        31: aload_0
        32: aload_1
        33: invokevirtual #45                 // Method com/tom/createores/OreData$Serialized.random:()F
        36: putfield      #49                 // Field randomMul:F
        39: return

  public com.tom.createores.OreData$Serialized save();
    Code:
         0: new           #14                 // class com/tom/createores/OreData$Serialized
         3: dup
         4: aload_0
         5: getfield      #19                 // Field loaded:Z
         8: aload_0
         9: getfield      #34                 // Field recipe:Lnet/minecraft/resources/ResourceLocation;
        12: invokestatic  #53                 // Method java/util/Optional.ofNullable:(Ljava/lang/Object;)Ljava/util/Optional;
        15: aload_0
        16: getfield      #41                 // Field extractedAmount:J
        19: aload_0
        20: getfield      #49                 // Field randomMul:F
        23: invokespecial #57                 // Method com/tom/createores/OreData$Serialized."<init>":(ZLjava/util/Optional;JF)V
        26: areturn

  public void setRecipe(net.minecraft.resources.ResourceLocation);
    Code:
         0: aload_0
         1: aload_1
         2: putfield      #34                 // Field recipe:Lnet/minecraft/resources/ResourceLocation;
         5: return

  public net.minecraft.resources.ResourceLocation getRecipeId();
    Code:
         0: aload_0
         1: getfield      #34                 // Field recipe:Lnet/minecraft/resources/ResourceLocation;
         4: areturn

  public net.minecraft.world.item.crafting.RecipeHolder<com.tom.createores.recipe.VeinRecipe> getRecipe(net.minecraft.world.item.crafting.RecipeManager);
    Code:
         0: aload_0
         1: getfield      #34                 // Field recipe:Lnet/minecraft/resources/ResourceLocation;
         4: ifnull        41
         7: aload_1
         8: aload_0
         9: getfield      #34                 // Field recipe:Lnet/minecraft/resources/ResourceLocation;
        12: invokevirtual #60                 // Method net/minecraft/world/item/crafting/RecipeManager.byKey:(Lnet/minecraft/resources/ResourceLocation;)Ljava/util/Optional;
        15: invokedynamic #66,  0             // InvokeDynamic #0:test:()Ljava/util/function/Predicate;
        20: invokevirtual #70                 // Method java/util/Optional.filter:(Ljava/util/function/Predicate;)Ljava/util/Optional;
        23: invokedynamic #74,  0             // InvokeDynamic #1:apply:()Ljava/util/function/Function;
        28: invokevirtual #78                 // Method java/util/Optional.map:(Ljava/util/function/Function;)Ljava/util/Optional;
        31: aconst_null
        32: invokevirtual #26                 // Method java/util/Optional.orElse:(Ljava/lang/Object;)Ljava/lang/Object;
        35: checkcast     #82                 // class net/minecraft/world/item/crafting/RecipeHolder
        38: goto          42
        41: aconst_null
        42: areturn

  public boolean isLoaded();
    Code:
         0: aload_0
         1: getfield      #19                 // Field loaded:Z
         4: ireturn

  public long getResourcesRemaining(com.tom.createores.recipe.VeinRecipe);
    Code:
         0: aload_1
         1: invokevirtual #84                 // Method com/tom/createores/recipe/VeinRecipe.isFinite:()Lcom/tom/createores/util/ThreeState;
         4: getstatic     #90                 // Field com/tom/createores/util/ThreeState.NEVER:Lcom/tom/createores/util/ThreeState;
         7: if_acmpeq     82
        10: aload_1
        11: invokevirtual #84                 // Method com/tom/createores/recipe/VeinRecipe.isFinite:()Lcom/tom/createores/util/ThreeState;
        14: getstatic     #96                 // Field com/tom/createores/util/ThreeState.DEFAULT:Lcom/tom/createores/util/ThreeState;
        17: if_acmpne     28
        20: getstatic     #99                 // Field com/tom/createores/Config.defaultInfinite:Z
        23: ifeq          28
        26: lconst_0
        27: lreturn
        28: aload_1
        29: invokevirtual #104                // Method com/tom/createores/recipe/VeinRecipe.getMaxAmount:()F
        32: aload_1
        33: invokevirtual #107                // Method com/tom/createores/recipe/VeinRecipe.getMinAmount:()F
        36: fsub
        37: aload_0
        38: getfield      #49                 // Field randomMul:F
        41: fmul
        42: aload_1
        43: invokevirtual #107                // Method com/tom/createores/recipe/VeinRecipe.getMinAmount:()F
        46: fadd
        47: f2d
        48: dstore_2
        49: dload_2
        50: getstatic     #110                // Field com/tom/createores/Config.finiteAmountBase:I
        53: i2d
        54: dmul
        55: invokestatic  #114                // Method java/lang/Math.round:(D)J
        58: lstore        4
        60: aload_0
        61: getfield      #41                 // Field extractedAmount:J
        64: lload         4
        66: lcmp
        67: iflt          74
        70: ldc2_w        #120                // long -1l
        73: lreturn
        74: lload         4
        76: aload_0
        77: getfield      #41                 // Field extractedAmount:J
        80: lsub
        81: lreturn
        82: lconst_0
        83: lreturn

  public float getRandomMul();
    Code:
         0: aload_0
         1: getfield      #49                 // Field randomMul:F
         4: freturn

  public void extract(int);
    Code:
         0: aload_0
         1: dup
         2: getfield      #41                 // Field extractedAmount:J
         5: iload_1
         6: i2l
         7: ladd
         8: putfield      #41                 // Field extractedAmount:J
        11: return

  public boolean canExtract(net.minecraft.world.level.Level, net.minecraft.core.BlockPos);
    Code:
         0: getstatic     #122                // Field com/tom/createores/Config.maxExtractorsPerVein:I
         3: ifne          8
         6: iconst_1
         7: ireturn
         8: aload_0
         9: getfield      #125                // Field extractors:Ljava/util/Set;
        12: ifnonnull     39
        15: aload_0
        16: new           #129                // class java/util/HashSet
        19: dup
        20: invokespecial #131                // Method java/util/HashSet."<init>":()V
        23: putfield      #125                // Field extractors:Ljava/util/Set;
        26: aload_0
        27: getfield      #125                // Field extractors:Ljava/util/Set;
        30: aload_2
        31: invokeinterface #132,  2          // InterfaceMethod java/util/Set.add:(Ljava/lang/Object;)Z
        36: pop
        37: iconst_1
        38: ireturn
        39: aload_0
        40: getfield      #125                // Field extractors:Ljava/util/Set;
        43: aload_2
        44: invokeinterface #138,  2          // InterfaceMethod java/util/Set.contains:(Ljava/lang/Object;)Z
        49: ifeq          54
        52: iconst_1
        53: ireturn
        54: aload_0
        55: getfield      #125                // Field extractors:Ljava/util/Set;
        58: aload_1
        59: invokedynamic #141,  0            // InvokeDynamic #2:test:(Lnet/minecraft/world/level/Level;)Ljava/util/function/Predicate;
        64: invokeinterface #144,  2          // InterfaceMethod java/util/Set.removeIf:(Ljava/util/function/Predicate;)Z
        69: pop
        70: aload_0
        71: getfield      #125                // Field extractors:Ljava/util/Set;
        74: invokeinterface #148,  1          // InterfaceMethod java/util/Set.size:()I
        79: getstatic     #122                // Field com/tom/createores/Config.maxExtractorsPerVein:I
        82: if_icmpge     98
        85: aload_0
        86: getfield      #125                // Field extractors:Ljava/util/Set;
        89: aload_2
        90: invokeinterface #132,  2          // InterfaceMethod java/util/Set.add:(Ljava/lang/Object;)Z
        95: pop
        96: iconst_1
        97: ireturn
        98: iconst_0
        99: ireturn

  public void setRandomMul(float);
    Code:
         0: aload_0
         1: fload_1
         2: putfield      #49                 // Field randomMul:F
         5: return

  public void setLoaded(boolean);
    Code:
         0: aload_0
         1: iload_1
         2: putfield      #19                 // Field loaded:Z
         5: return

  public void setExtractedAmount(long);
    Code:
         0: aload_0
         1: lload_1
         2: putfield      #41                 // Field extractedAmount:J
         5: return

  public void populate(net.minecraft.world.level.chunk.LevelChunk);
    Code:
         0: aload_1
         1: invokestatic  #152                // Method com/tom/createores/OreVeinGenerator.pick:(Lnet/minecraft/world/level/chunk/LevelChunk;)Lnet/minecraft/world/item/crafting/RecipeHolder;
         4: astore_2
         5: aload_2
         6: ifnull        32
         9: aload_1
        10: invokestatic  #158                // Method com/tom/createores/OreVeinGenerator.rngFromChunk:(Lnet/minecraft/world/level/chunk/LevelChunk;)Lnet/minecraft/util/RandomSource;
        13: astore_3
        14: aload_0
        15: aload_2
        16: invokevirtual #162                // Method net/minecraft/world/item/crafting/RecipeHolder.id:()Lnet/minecraft/resources/ResourceLocation;
        19: putfield      #34                 // Field recipe:Lnet/minecraft/resources/ResourceLocation;
        22: aload_0
        23: aload_3
        24: invokeinterface #166,  1          // InterfaceMethod net/minecraft/util/RandomSource.nextFloat:()F
        29: putfield      #49                 // Field randomMul:F
        32: aload_0
        33: iconst_1
        34: putfield      #19                 // Field loaded:Z
        37: return

  private static boolean lambda$canExtract$2(net.minecraft.world.level.Level, net.minecraft.core.BlockPos);
    Code:
         0: aload_0
         1: aload_1
         2: invokevirtual #171                // Method net/minecraft/world/level/Level.getBlockEntity:(Lnet/minecraft/core/BlockPos;)Lnet/minecraft/world/level/block/entity/BlockEntity;
         5: instanceof    #177                // class com/tom/createores/block/entity/IDrill
         8: ifne          15
        11: iconst_1
        12: goto          16
        15: iconst_0
        16: ireturn

  private static net.minecraft.world.item.crafting.RecipeHolder lambda$getRecipe$1(net.minecraft.world.item.crafting.RecipeHolder);
    Code:
         0: aload_0
         1: areturn

  private static boolean lambda$getRecipe$0(net.minecraft.world.item.crafting.RecipeHolder);
    Code:
         0: aload_0
         1: invokevirtual #179                // Method net/minecraft/world/item/crafting/RecipeHolder.value:()Lnet/minecraft/world/item/crafting/Recipe;
         4: instanceof    #85                 // class com/tom/createores/recipe/VeinRecipe
         7: ireturn

  static {};
    Code:
         0: getstatic     #183                // Field com/tom/createores/OreData$Serialized.CODEC:Lcom/mojang/serialization/Codec;
         3: invokedynamic #187,  0            // InvokeDynamic #3:apply:()Ljava/util/function/Function;
         8: invokedynamic #188,  0            // InvokeDynamic #4:apply:()Ljava/util/function/Function;
        13: invokeinterface #189,  3          // InterfaceMethod com/mojang/serialization/Codec.xmap:(Ljava/util/function/Function;Ljava/util/function/Function;)Lcom/mojang/serialization/Codec;
        18: putstatic     #195                // Field CODEC:Lcom/mojang/serialization/Codec;
        21: return
}
